m9g/__init__.py
m9g/exceptions.py
m9g/fields.py
m9g-0.0.6.dist-info/LICENSE
m9g-0.0.6.dist-info/METADATA
m9g-0.0.6.dist-info/WHEEL
m9g-0.0.6.dist-info/top_level.txt
m9g-0.0.6.dist-info/RECORD
