Metadata-Version: 2.1
Name: m9g
Version: 0.0.6
Summary: Define models for communication between components, handling MarshallinG (m9g)
Home-page: https://github.com/radiocutfm/m9g
Author: Lambda Sistemas
Author-email: desarrollo@lambdasistemas.com.ar
License: UNKNOWN
Project-URL: Bug Reports, https://github.com/radiocutfm/m9g/issues
Project-URL: Funding, https://donate.pypi.org
Project-URL: Say Thanks!, https://saythanks.io/to/guillermo.narvaja%40radiocut.fm
Project-URL: Source, https://github.com/radiocutfm/m9g/
Keywords: marshalling serialize communication model
Platform: UNKNOWN
Classifier: Topic :: Software Development :: Object Brokering
Classifier: Development Status :: 3 - Alpha
Classifier: Intended Audience :: Developers
Classifier: License :: OSI Approved :: MIT License
Classifier: Programming Language :: Python :: 2.7
Classifier: Programming Language :: Python :: 3
Classifier: Programming Language :: Python :: 3.6
Classifier: Programming Language :: Python :: 3.7
Classifier: Programming Language :: Python :: 3.8
Requires-Python: >=2.7, !=3.0.*, !=3.1.*, !=3.2.*, !=3.3.*, !=3.4.*, !=3.5.*, <4
Requires-Dist: future
Requires-Dist: future-fstrings
Provides-Extra: dev
Requires-Dist: check-manifest ; extra == 'dev'
Provides-Extra: test
Requires-Dist: coverage ; extra == 'test'
